pyraphtory_jvm
tests
